s3/__init__.py
s3/client.py
topmind_s3-3.0.0.dist-info/METADATA
topmind_s3-3.0.0.dist-info/RECORD
topmind_s3-3.0.0.dist-info/WHEEL
topmind_s3-3.0.0.dist-info/top_level.txt
